<annotation>
	<folder>Imagenes</folder>
	<filename>1167.jpg</filename>
	<path>/home/alejandro/Documents/Puig/Youtube/Deteccion de Objetos/Imagenes/1167.jpg</path>
	<source>
		<database>Unknown</database>
	</source>
	<size>
		<width>500</width>
		<height>403</height>
		<depth>3</depth>
	</size>
	<segmented>0</segmented>
	<object>
		<name>Tigre</name>
		<pose>Unspecified</pose>
		<truncated>0</truncated>
		<difficult>0</difficult>
		<bndbox>
			<xmin>177</xmin>
			<ymin>97</ymin>
			<xmax>351</xmax>
			<ymax>201</ymax>
		</bndbox>
	</object>
</annotation>
